fppy-0.0.18.post6.dist-info/licenses/LICENSE.txt
fpy/__init__.py
fpy/composable/__init__.py
fpy/composable/collections.py
fpy/composable/composable.py
fpy/composable/function.py
fpy/composable/transparent.py
fpy/control/__init__.py
fpy/control/applicative.py
fpy/control/functor.py
fpy/control/monad.py
fpy/control/natural_transform.py
fpy/data/__init__.py
fpy/data/cont.py
fpy/data/either.py
fpy/data/forgetful.py
fpy/data/function.py
fpy/data/maybe.py
fpy/data/state.py
fpy/debug/__init__.py
fpy/debug/debug.py
fpy/experimental/__init__.py
fpy/experimental/case.py
fpy/experimental/do.py
fpy/parsec/__init__.py
fpy/parsec/parsec.py
fpy/tests/__init__.py
fpy/tests/test_composable.py
fpy/tests/test_cont.py
fpy/tests/test_ctx_do.py
fpy/tests/test_do.py
fpy/tests/test_either.py
fpy/tests/test_function.py
fpy/tests/test_maybe.py
fpy/tests/test_parsec.py
fpy/tests/test_pat.py
fpy/tests/test_state.py
fpy/utils/__init__.py
fpy/utils/placeholder.py
fppy-0.0.18.post6.dist-info/METADATA
fppy-0.0.18.post6.dist-info/WHEEL
fppy-0.0.18.post6.dist-info/top_level.txt
fppy-0.0.18.post6.dist-info/RECORD
